{"numberOfItems": 11,
  "asanas": [
    {
      "asanaName": "Обратна положба",
      "sanskritName": "Viparita Karani",
      "asanaDetails": "Комплетно јогиско дишење како прамајама техника се изведува од седечка положба во која грбот треба да е исправен....",
      "asanaImages": "viparita_karani",
      "asanaCategory": "beginner"
    },
    {
      "asanaName": "Триаголник",
      "sanskritName": "Trikonasana",
      "asanaDetails": "Комплетно јогиско дишење како прамајама техника се изведува од седечка положба во која грбот треба да е исправен....",
      "asanaImages": "trikonasana",
      "asanaCategory": "beginner"
    },
    {
      "asanaName": "Чамец",
      "sanskritName": "Naukasana",
      "asanaDetails": "Комплетно јогиско дишење како прамајама техника се изведува од седечка положба во која грбот треба да е исправен....",
      "asanaImages": "naukasana",
      "asanaCategory": "beginner"
    },
    {
      "asanaName": "Вертикална штипалка",
      "sanskritName": "Uttanasana",
      "asanaDetails": "Комплетно јогиско дишење како прамајама техника се изведува од седечка положба во која грбот треба да е исправен....",
      "asanaImages": "uttanasana",
      "asanaCategory": "beginner"
    },
    {
      "asanaName": "Свеќа",
      "sanskritName": "Sarvangasana",
      "asanaDetails": "Комплетно јогиско дишење како прамајама техника се изведува од седечка положба во која грбот треба да е исправен....",
      "asanaImages": "sarvangasana",
      "asanaCategory": "intermediate"
    },
    {
      "asanaName": "Камила",
      "sanskritName": "Ustrasana",
      "asanaDetails": "Комплетно јогиско дишење како прамајама техника",
      "asanaImages": "ustrasana",
      "asanaCategory": "advanced"
    },
    {
      "asanaName": "Лесна седечка положба со торзија",
      "sanskritName": "Parivrtta Sukhasana",
      "asanaDetails": "Комплетно јогиско дишење како прамајама техника",
      "asanaImages": "parivrtta_sukhasana",
      "asanaCategory": "beginner"
    },
    {
      "asanaName": "Воин 1",
      "sanskritName": "Virasana 1",
      "asanaDetails": "Комплетно јогиско дишење како прамајама техника",
      "asanaImages": "virasana1",
      "asanaCategory": "intermediate"
    },
    {
      "asanaName": "Положба на поздрав",
      "sanskritName": "Namaskarasana",
      "asanaDetails": "Комплетно јогиско дишење како прамајама техника",
      "asanaImages": "namaskarasana",
      "asanaCategory": "beginner"
    },
    {
      "asanaName": "Кобра",
      "sanskritName": "Bhujangasana",
      "asanaDetails": "Комплетно јогиско дишење како прамајама техника",
      "asanaImages": "bhujangasana",
      "asanaCategory": "beginner"
    },
    {
      "asanaName": "Мачка",
      "sanskritName": "Marjariasana",
      "asanaDetails": "Комплетно јогиско дишење како прамајама техника",
      "asanaImages": "marjariasana",
      "asanaCategory": "beginner"
    }
  ]
}